buildinfo_om-0.7.0.dist-info/METADATA
buildinfo_om-0.7.0.dist-info/WHEEL
buildinfo_om-0.7.0.dist-info/licenses/LICENSE
buildinfo_om-0.7.0.dist-info/licenses/LICENSE.Apache
buildinfo_om-0.7.0.dist-info/licenses/LICENSE.mit
buildinfo_om/__init__.py
buildinfo_om/_builder.py
buildinfo_om/_loadsave.py
buildinfo_om/_merge.py
buildinfo_om/_model.py
buildinfo_om/_vcs.py
buildinfo_om/py.typed
buildinfo_om-0.7.0.dist-info/RECORD
