Metadata-Version: 2.1
Name: buildinfo-om
Version: 0.7.0
Summary: JFrog BuildInfo ObjectModel written in python
Author-Email: Carsten Igel <cig@bite-that-bit.de>
License: Apache 2.0 OR MIT
Requires-Python: >=3.11
Requires-Dist: dacite>=1.8.1
Requires-Dist: makefun>=1.15.2
